nebari_workflow_controller/__init__.py
nebari_workflow_controller/__main__.py
nebari_workflow_controller/_version.py
nebari_workflow_controller/app.py
nebari_workflow_controller/exceptions.py
nebari_workflow_controller/models.py
nebari_workflow_controller/nwc.py
nebari_workflow_controller/utils.py
nebari_workflow_controller-2023.7.1.dist-info/METADATA
nebari_workflow_controller-2023.7.1.dist-info/WHEEL
nebari_workflow_controller-2023.7.1.dist-info/licenses/LICENSE
nebari_workflow_controller-2023.7.1.dist-info/RECORD
