Metadata-Version: 2.1
Name: nebari-workflow-controller
Version: 2023.7.1
Summary: An admission controller for argo workflows in Nebari
Project-URL: Documentation, https://github.com/nebari-dev/nebari-workflow-controller
Project-URL: Source, https://github.com/nebari-dev/nebari-workflow-controller
Author-email: Nebari development team <internal-it@quansight.com>
License-Expression: BSD-3-Clause
License-File: LICENSE
Keywords: admission-controller,argo-workflows,fastapi,kubernetes,nebari
Classifier: Development Status :: 3 - Alpha
Classifier: Intended Audience :: Developers
Classifier: Intended Audience :: System Administrators
Classifier: Programming Language :: Python :: 3
Classifier: Programming Language :: Python :: 3.8
Classifier: Programming Language :: Python :: 3.9
Classifier: Programming Language :: Python :: 3.10
Classifier: Topic :: Software Development :: Build Tools
Requires-Python: >=3.8
Requires-Dist: fastapi==0.95.1
Requires-Dist: jsonpatch==1.32
Requires-Dist: kubernetes==26.1.0
Requires-Dist: pydantic==1.10.7
Requires-Dist: python-keycloak==2.15.3
Requires-Dist: uvicorn==0.21.1
Provides-Extra: dev
Requires-Dist: black==22.3.0; extra == 'dev'
Requires-Dist: build; extra == 'dev'
Requires-Dist: flake8==3.8.4; extra == 'dev'
Requires-Dist: pre-commit; extra == 'dev'
Requires-Dist: pytest; extra == 'dev'
Requires-Dist: pytest-mock; extra == 'dev'
Requires-Dist: pyyaml; extra == 'dev'
